collective/ftwslacker/__init__.py
collective/ftwslacker/configure.zcml
collective/ftwslacker/interfaces.py
collective/ftwslacker/slack_notifier.py
collective/ftwslacker/testing.py
collective/ftwslacker/tests/__init__.py
collective/ftwslacker/tests/test_slack_notifier.py
collective_ftwslacker-2.0.0a1.dist-info/METADATA
collective_ftwslacker-2.0.0a1.dist-info/WHEEL
collective_ftwslacker-2.0.0a1.dist-info/entry_points.txt
collective_ftwslacker-2.0.0a1.dist-info/top_level.txt
collective_ftwslacker-2.0.0a1.dist-info/RECORD
